gitmate/__init__.py
gitmate/__main__.py
gitmate/main.py
gitmate/models.py
gitmate/utils.py
gitmate-0.0.3.dist-info/METADATA
gitmate-0.0.3.dist-info/WHEEL
gitmate-0.0.3.dist-info/entry_points.txt
gitmate-0.0.3.dist-info/RECORD
