Metadata-Version: 2.1
Name: gitmate
Version: 0.0.3
Summary: 
Author: Rohit Gupta
Author-email: rohitgr1998@gmail.com
Requires-Python: >=3.9,<4.0
Classifier: Programming Language :: Python :: 3
Classifier: Programming Language :: Python :: 3.9
Classifier: Programming Language :: Python :: 3.10
Classifier: Programming Language :: Python :: 3.11
Requires-Dist: halo (>=0.0.31,<0.0.32)
Requires-Dist: requests (>=2.28.2,<3.0.0)
Requires-Dist: rich (>=13.3.2,<14.0.0)
Requires-Dist: typer (>=0.7.0,<0.8.0)
